[{"data":null},{"data":null},{"data":null},{"data":null},{"data":null},{"data":null},{"data":null},{"data":null},{"data":null},{"data":null},{"data":null},{"data":null},{"data":null},{"data":null},{"data":null},{"data":null},{"data":null},{"data":null},{"data":null},{"id":"222286","data":{"info":{"title":"Sekiro: Shadows Die Twice - GOTY Edition","steamAppID":"814380","thumb":"https://cdn.cloudflare.steamstatic.com/steam/apps/814380/capsule_sm_120.jpg?t=1678991267"},"cheapestPriceEver":{"price":"29.99","date":1624557434},"deals":[{"storeID":"1","dealID":"Hry4PjzwGVs%2FN4gV6%2FWbQ0CJAgWSzZ%2BhpFCb2APxQoA%3D","price":"59.99","retailPrice":"59.99","savings":"0.000000"}]}},{"id":"186657","data":{"info":{"title":"Dark Souls Remastered","steamAppID":"570940","thumb":"https://cdn.cloudflare.steamstatic.com/steam/apps/570940/capsule_sm_120.jpg?t=1700659167"},"cheapestPriceEver":{"price":"13.99","date":1587025294},"deals":[{"storeID":"23","dealID":"pPUxcxnCYGae1jXGVO2OxCRhK4Gndu5QNAxMIxHmnoA%3D","price":"33.17","retailPrice":"39.99","savings":"17.054264"},{"storeID":"29","dealID":"xjIzVz3uhTgAs333RvNiqAi%2FdhXKupvtDVotCBl1w0g%3D","price":"33.59","retailPrice":"39.99","savings":"16.004001"},{"storeID":"15","dealID":"oP1rJxSr%2Ftl43f0v9iaR6IDkDPeGDx0I%2F7iAnLdM7bE%3D","price":"34.79","retailPrice":"39.99","savings":"13.003251"},{"storeID":"21","dealID":"Xk7r3a1LTu7gUegx8K3jJMa5y7efkeegEhc97h8YG3M%3D","price":"34.99","retailPrice":"39.99","savings":"12.503126"},{"storeID":"27","dealID":"snY5YwdOiFvjFwrSLvtC4RZGcCQyYvTkGxLcZy6wy5E%3D","price":"35.99","retailPrice":"39.99","savings":"10.002501"},{"storeID":"33","dealID":"ZOfk3vICrx%2F5sdd9PeyzvkgSLmq%2FLvD187NbQ0W7DXk%3D","price":"37.99","retailPrice":"39.99","savings":"5.001250"},{"storeID":"24","dealID":"D3BLy8%2BTIn0B7lUk9JZ50RxAOLs9B%2BSTFcyHFZkoNJc%3D","price":"39.99","retailPrice":"39.99","savings":"0.000000"},{"storeID":"1","dealID":"MV0FVF9VvgHtBSZnQTPv13EAEAOZI%2B7g4v6SsizRg%2Bw%3D","price":"39.99","retailPrice":"39.99","savings":"0.000000"},{"storeID":"11","dealID":"6wVniGmwQmxAWhOOTlRIQL4Z%2BRYFiWwrWwV5nz01WXA%3D","price":"39.99","retailPrice":"39.99","savings":"0.000000"},{"storeID":"30","dealID":"inDv6JXebJZiECk16DFqSRm1cfmRWfWcbPax6kIo4Dw%3D","price":"39.99","retailPrice":"39.99","savings":"0.000000"},{"storeID":"3","dealID":"injteTvpqskl%2BPqkbIVqMHbxJ2V9G4TwGMvRGafzF9E%3D","price":"39.99","retailPrice":"39.99","savings":"0.000000"},{"storeID":"35","dealID":"lIcWwle75yhtdbhHAHSe2afXqhw%2BKSY%2BEVx1mT1FpKA%3D","price":"39.99","retailPrice":"39.99","savings":"0.000000"},{"storeID":"2","dealID":"KzrE0gXy3uAfKzXzwEw9GZKcHNhiHXYWRxt7zNJH4Hc%3D","price":"39.99","retailPrice":"39.99","savings":"0.000000"},{"storeID":"34","dealID":"nOwOdl6NND2OJKtbyvBeIGXQ59F9A4uSi5zPe5RPVk4%3D","price":"43.99","retailPrice":"43.99","savings":"0.000000"}]}}]